<annotation>
	<folder></folder>
	<filename>1204_Zone_2_Mine_1cm_depth__1-0m_TemperatureInCenter__29A-C_jpg.rf.7ec0628acbb41a6200f64f93bcba9738.jpg</filename>
	<path>1204_Zone_2_Mine_1cm_depth__1-0m_TemperatureInCenter__29A-C_jpg.rf.7ec0628acbb41a6200f64f93bcba9738.jpg</path>
	<source>
		<database>roboflow.com</database>
	</source>
	<size>
		<width>740</width>
		<height>480</height>
		<depth>3</depth>
	</size>
	<segmented>0</segmented>
	<object>
		<name>landmines</name>
		<pose>Unspecified</pose>
		<truncated>0</truncated>
		<difficult>0</difficult>
		<occluded>0</occluded>
		<bndbox>
			<xmin>386</xmin>
			<xmax>462</xmax>
			<ymin>152</ymin>
			<ymax>221</ymax>
		</bndbox>
	</object>
</annotation>
